SciGlassPlus/__init__.py
SciGlassPlus/columnNames.py
SciGlassPlus/load.py
sciglassplus-1.0.3.dist-info/licenses/LICENSE.txt
sciglassplus-1.0.3.dist-info/METADATA
sciglassplus-1.0.3.dist-info/WHEEL
sciglassplus-1.0.3.dist-info/top_level.txt
sciglassplus-1.0.3.dist-info/RECORD
