Metadata-Version: 2.4
Name: SciGlassPlus
Version: 1.0.3
License: MIT License
Requires-Python: >=3.10
License-File: LICENSE.txt
Requires-Dist: numpy>=1.26.4
Requires-Dist: pandas>=2.3.2
Requires-Dist: openpyxl>=3.1.5
Dynamic: license-file
